<?xml version="1.0" encoding="utf8"?><GeometryTopologyData><numDimensions>3</numDimensions><coordinateSystem>RAS</coordinateSystem><Point><ChestRegion>0</ChestRegion><ChestType>2</ChestType><Coordinate><value>15.978850</value><value>28.371002</value><value>-168.000000</value></Coordinate></Point><Point><ChestRegion>0</ChestRegion><ChestType>77</ChestType><Coordinate><value>68.173416</value><value>2.910238</value><value>-168.000000</value></Coordinate></Point><Point><ChestRegion>0</ChestRegion><ChestType>77</ChestType><Coordinate><value>-30.487045</value><value>-49.920847</value><value>-168.000000</value></Coordinate></Point><Point><ChestRegion>0</ChestRegion><ChestType>78</ChestType><Coordinate><value>36.983980</value><value>-64.560786</value><value>-168.000000</value></Coordinate></Point><Point><ChestRegion>0</ChestRegion><ChestType>94</ChestType><Coordinate><value>41.439614</value><value>46.193537</value><value>-168.000000</value></Coordinate></Point><Point><ChestRegion>0</ChestRegion><ChestType>96</ChestType><Coordinate><value>10.250178</value><value>-13.639258</value><value>-168.000000</value></Coordinate></Point><Point><ChestRegion>0</ChestRegion><ChestType>97</ChestType><Coordinate><value>57.352591</value><value>-48.011290</value><value>-168.000000</value></Coordinate></Point></GeometryTopologyData>